boolexpr/__init__.py
boolexpr/_boolexpr.cpython-35m-darwin.so
boolexpr/misc.py
boolexpr/util.py
boolexpr/wrap.py
boolexpr-2.4.dist-info/DESCRIPTION.rst
boolexpr-2.4.dist-info/METADATA
boolexpr-2.4.dist-info/RECORD
boolexpr-2.4.dist-info/WHEEL
boolexpr-2.4.dist-info/metadata.json
boolexpr-2.4.dist-info/top_level.txt
