Metadata-Version: 2.0
Name: boolexpr
Version: 2.4
Summary: Boolean Expressions
Home-page: http://www.boolexpr.org
Author: Chris Drake
Author-email: cjdrake@gmail.com
License: Apache 2.0
Download-URL: https://github.com/cjdrake/boolexpr/archive/v2.3.tar.gz
Platform: UNKNOWN
Classifier: Development Status :: 5 - Production/Stable
Classifier: License :: OSI Approved :: Apache Software License
Classifier: Programming Language :: C++
Classifier: Programming Language :: Python
Classifier: Programming Language :: Python :: 3.4
Classifier: Programming Language :: Python :: 3.5
Classifier: Topic :: Scientific/Engineering :: Electronic Design Automation (EDA)
Classifier: Topic :: Scientific/Engineering :: Mathematics
Requires-Dist: cffi (>=1.5.0)
